moon_utilities/__init__.py
moon_utilities/auth_functions.py
moon_utilities/exceptions.py
moon_utilities/generate_opst_policy.py
moon_utilities/install.py
moon_utilities/invalided_functions.py
moon_utilities/json_utils.py
moon_utilities/security_functions.py
moon_utilities-0.8.dist-info/LICENSE
moon_utilities-0.8.dist-info/METADATA
moon_utilities-0.8.dist-info/WHEEL
moon_utilities-0.8.dist-info/entry_points.txt
moon_utilities-0.8.dist-info/top_level.txt
moon_utilities-0.8.dist-info/RECORD
